MANIFEST.in
collective.contentstats-configure.zcml
setup.py
collective/__init__.py
collective.contentstats.egg-info/PKG-INFO
collective.contentstats.egg-info/SOURCES.txt
collective.contentstats.egg-info/dependency_links.txt
collective.contentstats.egg-info/entry_points.txt
collective.contentstats.egg-info/namespace_packages.txt
collective.contentstats.egg-info/not-zip-safe
collective.contentstats.egg-info/requires.txt
collective.contentstats.egg-info/top_level.txt
collective/contentstats/README.txt
collective/contentstats/__init__.py
collective/contentstats/configure.zcml
collective/contentstats/profiles.zcml
collective/contentstats/tests.py
collective/contentstats/version.txt
collective/contentstats/browser/__init__.py
collective/contentstats/browser/configure.zcml
collective/contentstats/browser/summary-statistics.pt
collective/contentstats/browser/summary-statistics.py
collective/contentstats/profiles/default/actionicons.xml
collective/contentstats/profiles/default/collective.contentstats_various.txt
collective/contentstats/profiles/default/controlpanel.xml
collective/contentstats/profiles/default/metadata.xml
docs/HISTORY.txt
docs/INSTALL.txt
docs/LICENSE.GPL
docs/LICENSE.txt