Metadata-Version: 1.0
Name: collective.contentstats
Version: 1.0.1
Summary: A configlet for Plone showing some content statistics (type/state)
Home-page: http://svn.plone.org/svn/collective/
Author: Raphael Ritz
Author-email: raphael.ritz@incf.org
License: GPL
Keywords: web zope plone configlet content reporting
Platform: UNKNOWN
Classifier: Framework :: Plone
Classifier: Programming Language :: Python
Classifier: Topic :: Software Development :: Libraries :: Python Modules
